fsdata/__init__.py
fsdata/collection.py
fsdata/config.py
fsdata/utils.py
fsdata-0.0.5.dist-info/WHEEL
fsdata-0.0.5.dist-info/METADATA
fsdata-0.0.5.dist-info/RECORD
