Metadata-Version: 2.4
Name: fsdata
Version: 0.0.5
Summary: Simple data access layer over fsspec
Keywords: data-access,pathlib,fsspec
Author: Furechan
Author-email: Furechan <furechan@xsmail.com>
License-Expression: MIT
Classifier: Programming Language :: Python :: 3
Classifier: License :: OSI Approved :: MIT License
Classifier: Operating System :: OS Independent
Requires-Dist: universal-pathlib
Requires-Dist: pyarrow
Requires-Dist: pandas
Requires-Dist: s3fs>=2025.1.0 ; extra == 'all'
Requires-Dist: s3fs>=2025.1.0 ; extra == 's3'
Requires-Python: >=3.10
Provides-Extra: all
Provides-Extra: s3
